jonckheere_test/__init__.py
jonckheere_test/_core.py
jonckheere_test-0.1.1.dist-info/METADATA
jonckheere_test-0.1.1.dist-info/WHEEL
jonckheere_test-0.1.1.dist-info/licenses/LICENSE
jonckheere_test-0.1.1.dist-info/RECORD
