Metadata-Version: 2.4
Name: jonckheere-test
Version: 0.1.1
Summary: Jonckheere-Terpstra test for ordered alternatives
Project-URL: Homepage, https://github.com/ScarWar/jonckheere-test
Project-URL: Repository, https://github.com/ScarWar/jonckheere-test
Project-URL: Issues, https://github.com/ScarWar/jonckheere-test/issues
Author: Ariel Bereslavsky
License: MIT
License-File: LICENSE
Keywords: hypothesis-testing,jonckheere,nonparametric,statistics,terpstra,trend-test
Classifier: Development Status :: 4 - Beta
Classifier: Intended Audience :: Science/Research
Classifier: License :: OSI Approved :: MIT License
Classifier: Operating System :: OS Independent
Classifier: Programming Language :: Python :: 3
Classifier: Programming Language :: Python :: 3.9
Classifier: Programming Language :: Python :: 3.10
Classifier: Programming Language :: Python :: 3.11
Classifier: Programming Language :: Python :: 3.12
Classifier: Programming Language :: Python :: 3.13
Classifier: Topic :: Scientific/Engineering :: Bio-Informatics
Classifier: Topic :: Scientific/Engineering :: Mathematics
Requires-Python: >=3.9
Requires-Dist: numpy>=1.21
Requires-Dist: scipy>=1.7
